{
  "aigisMod:TowerOfHeroes": {
    "NAME": "영걸의 탑",
    "DESCRIPTIONS": [
      "익숙한 영걸탑 계층에 도착했습니다. NL 탑을 관리하는 영걸들은 당신에게 선택지를 제시했습니다: NL 영걸의 힘을 일부 빌려가거나 NL 혹은 NL 스스로의 힘을 증명하고 전투를 통해 더 큰 힘을 얻는 것.",
      "자신의 선택을 믿으며, 당신은 그 층을 떠나 여정을 계속합니다.",
      "당신의 선택은 큰 힘을 가져다 줄 것입니다.",
      "당신은 그들의 기대에 응답했습니다."
    ],
    "OPTIONS": [
      "[힘을 빌리다] #g특별 #g영걸 #g카드를 #g획득합니다.",
      "[전투] #g특별 #g영걸 #g카드를 #g희귀 #g영걸 #g카드로 #g업그레이드합니다.",
      "[떠난다]",
      "덱에 추가할 영걸 카드를 선택하십시오.",
      "[힘을 빌리다] #g희귀 #g영걸 #g카드로 #g업그레이드합니다.",
      "[잠김] 희귀 영걸 카드로 업그레이드할 영걸 카드가 없습니다."
    ]
  },

  "aigisMod:AigisShrine": {
    "NAME": "아이기스 신전",
    "DESCRIPTIONS": [
      "익숙한 신전에 도착했습니다. NL 여신 아이기스를 모시는 신전입니다. NL 당신은 여신의 가호를 받을 수 있습니다.",
      "당신은 신전을 떠나 여정을 계속합니다."
    ],
    "OPTIONS": [
      "[기부] #g100 #b골드를 #g바치고 #g유물을 #g얻습니다.",
      "[기도] #g카드를 #g업그레이드합니다.",
      "[소환] #g20장 #b중 #g1장을 #b선택해 #g덱에 #g넣습니다.",
      "[떠난다]",
      "덱에 추가할 카드를 선택하십시오.",
      "[잠김] 골드가 부족합니다 (100).",
      "[잠김] 업그레이드할 카드가 없습니다.",
      "업그레이드할 카드를 고르십시오."
    ]
  },

  "aigisMod:MilitaryExercise": {
    "NAME": "군사훈련",
    "DESCRIPTIONS": [
      "제국군은 왕국군과의 합류지점에 도착했습니다. NL 원정 재개까지 시간이 남았기에 병력을 강화할 수 있을 것입니다.",
      "당신은 부대를 재편성하기로 했습니다.",
      "당신은 휘하 부대들과 훈련하기로 했습니다.",
      "당신은 새로운 힘에 눈뜨기 위해 전투를 결심합니다."
    ],
    "OPTIONS": [
      "[재편성] #g덱에 #g새로운 #g카드를 #g추가합니다.",
      "[훈련] #g카드를 #g업그레이드합니다.",
      "[전투] #r왕국군과 #r전투합니다.",
      "[떠난다]",
      "[잠김] 업그레이드할 카드가 없습니다.",
      "업그레이드할 카드를 고르십시오.",
      "[각성] #g유물을 #g얻습니다."
    ]
  },


  "aigisMod:CursedGem": {
    "NAME": "Cursed Gem",
    "DESCRIPTIONS": [
      "Before you lies a dead body, it holds a mysterious gem. NL You also see a gold plated chest in the room. You feel some power coming from the gems, but the chest also has your attention.",
      "With the gem in your hands now you can identify it comes from a cursed cult. You have the duty to safekeep it, but its power may come in handy.",
      "As suspected, it is a monsters."
    ],
    "OPTIONS": [
      "[Search] #gExamine #gthe #rgold #rchest?",
      "[Take the Gem] #gGain #ga #gRelic and #ra #rCurse.",
      "[Leave]",
      "[Fight]"
    ]
  },
  "aigisMod:TheVoice": {
    "NAME": "The Voice",
    "DESCRIPTIONS": [
      "Navigating trough the floor you suddenly lose your senses and you begin to hear a voice...",
      "You feel inspired and stronger for some reason.",
      "You feel a familiar strength within you.",
      "You should be more aware."
    ],
    "OPTIONS": [
      "[The Stars?] #gMax #gHP #b+8",
      "[Commander?] #gGain #ga #gRelic",
      "[Wake Up] Leave"
    ]
  },

  "aigisMod:VampireDeal": {
    "NAME": "Deal with a Vampire",
    "DESCRIPTIONS": [
      "You have a encounter with a powerful undead. NL She proposes to join your cause, but you don´t trust her words.",
      "You accepted the deal.",
      "You came to understand her goals.",
      "You refuse and resume your journey."
    ],
    "OPTIONS": [
      "[Recruit] #gGain #gan #gUncommon #gHero #gCard. #rGain #ra #rLethal #rCurse.",
      "[Fight] #gGain #ga #gRare #gHero #gCard #gand #gUpgrade #git.",
      "[Refuse]",
      "[Leave]",
      "[Recruit] #gGain #ga #grare #gHero #gCard."
    ]
  },
  "aigisMod:FallenReunion": {
    "NAME": "Fallen Reunion",
    "DESCRIPTIONS": [
      "Someone intercepts you. NL It might be an angel but it feels somewhat evil. NL You consider your options.",
      "It seems there is some goals in common.",
      "She says you passed her trial. ",
      "You managed to run away."
    ],
    "OPTIONS": [
      "[Talk] #gGain #gan #gUncommon #gHero #gCard.",
      "[Fight] #gGain #ga #gRare #gHero #gCard #gand #gUpgrade #git.",
      "[Escape] #rLose #b5 #rHP.",
      "[Recruit] #gGain #ga #grare #gHero #gCard.",
      "[LOCKED] You don't have a Release card.",
      "[Leave]"
    ]
  }
}
