{
  "CharTooltipsID": {
    "TEXT": [
      "ウィッチ", "敵に攻撃した時、一時的に #yスロー を与える。",
      "アーチャー", "このカードはトゲのような #y攻撃時 に発動する能力を #b無視 する。",
      "プリンセス", "あなたのデッキに #yプリンセス カードを1枚加えた時、 #y最大 #yHP が #b1 増加する。",
      "アンデッド", "このクラスは #y廃棄 された時 #b追加 効果が発動する。",
      "レアリティブラック", "このタイプのキャラクターは、 #yアップグレード の際に #y分岐 することがある。この特性は、レアカードだけが持つ。",
      "東の国", "このカードは #y東の国 を指名する効果の対象となる。",
      "英傑", "このカードは何度でもアップグレードができる。 NL #y英傑結晶 のレリックと #y英傑の塔 のイベントでのみ入手可能。",
      "白の帝国", "このカードは、 #y帝国 を指名する効果の対象となる。",
      "呪術師", "プレイした時、表示された #y呪い がデッキに入っていない場合、追加する。",
      "デーモン", "あなたのターンの開始時にこのカードが廃棄山にある場合、そのターンの間 #y本来 のコストから #b-1 して手札に加える。",
      "飛行隊", "プレイした時、 #yエアーシグナル を #b1 枚あなたの山札に加える。 #yエアーシグナル が廃棄されるごとにダメージが #b1 増加する。",
      "ネクロマンサー", " #yアンデッド が #y廃棄 されるたび、ダメージが #b1 増加する。防御されずにダメージを与えた時、 #yスケルトン を手札に #b1 枚加える。"
    ]
  },

  "AmbrosePDiscardAction": {
    "TEXT": [
      "捨てる (３つまで)",
      "捨てる"
    ]
  },

  "ArmorSmithAction": {
    "TEXT": [
      "アップグレード."
    ]
  },

  "CindyAction": {
    "TEXT": [
      "捨てる"
    ]
  },

  "CursedBoundaryAction": {
    "TEXT": [
      "捨てる"
    ]
  },

  "EasternMaidAction": {
    "TEXT": [
      "コストを減らすカードを選択する"
    ]
  },

  "DengunsCommandAction": {
    "TEXT": [
      "手札のカード1枚を山札の1番上に置く",
      "手札のカードを山札の1番上に置く",
      "山札に東の国カードがない…"
    ]
  },

  "LepuruAction": {
    "TEXT": [
      "山札に戻る",
      "山札に戻る"
    ]
  },

  "OldClergymanAction": {
    "TEXT": [
      "廃棄"
    ]
  },

  "SuzuneAction": {
    "TEXT": [
      "手札に加える1枚を選ぶ"
    ]
  },

  "SwordSmithAction": {
    "TEXT": [
      "アップグレード"
    ]
  },

  "TowaAction": {
    "TEXT": [
      "山札の1番上に置くウィッチを1枚選択",
      "山札の1番上に置くウィッチを2枚選択",
      "山札にウィッチカードがない…"
    ]
  },

  "VampireHunterDPAction": {
    "TEXT": [
      "廃棄する1枚を選ぶ"
    ]
  },

  "YashimaAction": {
    "TEXT": [
      "1枚のカードの効果をコピーする"
    ]
  },

  "PrincessMaidAction": {
    "TEXT": [
      "手札に加える1枚を選ぶ",
      "手札に加えるカードを選ぶ",
      "山札にプリンセスカードがない…"
    ]
  },

  "RisleyAction": {
    "TEXT": [
      "コストを1減少する"
    ]
  },

  "ShizukaAction": {
    "TEXT": [
      "捨てる",
      "手札に東の国カードがない…"
    ]
  },

  "KagerouAction": {
    "TEXT": [
      "捨てる"
    ]
  },

  "AirshipAction": {
    "TEXT": [
      "帝国カードを1枚手札に加える",
      "山札に帝国カードがない…"
    ]
  },

  "RuteKnightAction": {
    "TEXT": [
      "帝国騎士カードを1枚手札に加える",
      "山札に帝国騎士カードがない…"
    ]
  },

  "RuteStrikeAction": {
    "TEXT": [
      "ストライクを1枚手札に加える",
      "捨て札にストライクがない…"
    ]
  },

  "LilyAction": {
    "TEXT": [
      "手札から選んでプレイする（任意）"
    ]
  },

  "BlitzkriegAction": {
    "TEXT": [
      "プレイするカードを選ぶ（任意）",
      "手札からプレイするカードを1枚選ぶ（任意）",
      "選択"
    ]
  },

  "LieselotteAction": {
    "TEXT": [
      "捨てる（任意）"
    ]
  },

  "MephistoAction": {
    "TEXT": [
      "廃棄する帝国とデーモンカードを選ぶ（任意）",
      "山札に帝国とデーモンカードがない…"
    ]
  },
  "AuroraAction": {
    "TEXT": [
      "廃棄するカードを選ぶ（任意）"
    ]
  },
  "WhiteDevotionAction": {
    "TEXT": [
      "廃棄（任意）"
    ]
  },
  "CallingYouAction": {
    "TEXT": [
      "手札に加えるキャラクターを1枚選ぶ",
      "手札に加えるキャラクターを選ぶ",
      "捨て札に帝国カードがない…"
    ]
  },
  "AirSignalAction": {
    "TEXT": [
      "手札に加えるカードを1枚選択する",
      "手札に加えるカードを選択する",
      "捨て札に飛行隊カードがない…"
    ]
  },
  "DemonCommandAction": {
    "TEXT": [
      "廃棄"
    ]
  },
  "HelmineAction": {
    "TEXT": [
      "廃棄",
      "手札にカードがない…"
    ]
  },
  "StrikeModifStrings": {
    "TEXT": [
      "弱体.",
      "毒",
      " NL 弱体 ", " を与える。",
      " NL 毒 ", " を与える。",
      "鈍足.",
      " aigismod:鈍足 ", " を与える。 ",
      "エナジー",
      "エナジー", " を得る。"
    ]
  },
  "BelpheAction": {
    "TEXT": [
      "", " 枚廃棄する（任意）", "捨て札がない…"
    ]
  },
  "ImperialInventorAction": {
    "TEXT": [
      "アップグレード（任意）"
    ]
  },
  "MakaiCookingAction": {
    "TEXT": [
      "廃棄"
    ]
  },
  "NormaAction": {
    "TEXT": [
      "デーモンカードを ", " 枚まで廃棄する", "デーモンカードが捨て札にない…"
    ]
  },
  "OtherworldCallAction": {
    "TEXT": [
      "廃棄するデーモンカードを ", " 枚選ぶ", "デーモンカードが山札にない…"
    ]
  },
  "NatalieAction": {
    "TEXT": [
      "捨てる"
    ]
  },
  "TsugumiExhaustAction": {
    "TEXT": [
      "廃棄"
    ]
  },
  "TsugumiRecoverAction": {
    "TEXT": [
      "手札に加えるカードを1枚選ぶ",
      "東の国カードが捨て札にない…"
    ]
  },
  "EstrieAction": {
    "TEXT": [
      "廃棄するアンデッドカードを ", " 枚選択する", "アンデッドカードが捨て札にない…"
    ]
  },
  "SpookyPhenomenonAction": {
    "TEXT": [
      "廃棄"
    ]
  },
  "FedoraAction": {
    "TEXT": [
      "廃棄"
    ]
  },
  "TenguBlazeAction": {
    "TEXT": [
      "廃棄"
    ]
  },
  "UndeadWorldAction": {
    "TEXT": [
      "手札に加えるアンデット1枚を選ぶ", 
      "廃棄山にアンデッドカードがない…"
    ]
  },

  "HeroCrystalText": {
    "TEXT": [
      "英傑カードを見る。"
    ]
  },

  "SumireAction": {
    "TEXT": [
      "手札に加えるカード1枚を選ぶ",
      "山札に東の国カードも流星カードもない…"
    ]
  },

  "NielAction": {
    "TEXT": [
      "手札に加えるコスト1以下のカードを選ぶ",
      "捨て札にコスト1以下のカードがない…"
    ]
  },

  "ErunAction": {
    "TEXT": [
      "手札に加えるカード1枚を選ぶ",
      "山札に封印解除カードがない…"
    ]
  },

  "NephtyAction": {
    "TEXT": [
      "このターンの間、コストを下げる"
    ]
  },

  "VivianAction": {
    "TEXT": [
      "この戦闘中、コストを下げる"
    ]
  },

  "AngelMaidAction": {
    "TEXT": [
      "手札に加えるカードを1枚選ぶ",
      "手札に加えるカードを選ぶ",
      "山札に封印解除カードがない…"
    ]
  }
}
